teamhack_nmap/__init__.py
teamhack_nmap/__main__.py
teamhack_nmap/server.py
teamhack_nmap-0.0.4329.dist-info/METADATA
teamhack_nmap-0.0.4329.dist-info/WHEEL
teamhack_nmap-0.0.4329.dist-info/top_level.txt
teamhack_nmap-0.0.4329.dist-info/RECORD
