Metadata-Version: 2.1
Name: teamhack-nmap
Version: 0.0.4329
Summary: Hack the Box Team Support Services
Requires-Dist: flask
Provides-Extra: rel
Requires-Dist: twine ; extra == 'rel'
Provides-Extra: test
Requires-Dist: coverage ; extra == 'test'
Requires-Dist: pytest ; extra == 'test'
